OAS_wrapper/__init__.py
OAS_wrapper/annotate_sequence.py
OAS_wrapper/column_summary.py
OAS_wrapper/compare_sequence_to_germline.py
OAS_wrapper/germline_to_sequence_mappings.py
OAS_wrapper/imgt_parse.py
OAS_wrapper/main.py
OAS_wrapper/metadata_sequences.py
OAS_wrapper/plot_string_length_distribution.py
OAS_wrapper/tabulate_query_sequence.py
OAS_wrapper-1.1.dist-info/LICENSE
OAS_wrapper-1.1.dist-info/METADATA
OAS_wrapper-1.1.dist-info/WHEEL
OAS_wrapper-1.1.dist-info/top_level.txt
OAS_wrapper-1.1.dist-info/RECORD
