Metadata-Version: 2.1
Name: OAS_wrapper
Version: 1.1
Summary: Python package to parse Observed antibody sequence data for easy reporting, visualization, annotation and alignment.
Home-page: https://github.com/sridhara-omics/OAS_wrapper
Author: Viswanadham Sridhara
Author-email: Sridhara.Utils@gmail.com
Classifier: Development Status :: 3 - Alpha
Classifier: Intended Audience :: Developers
Classifier: License :: OSI Approved :: MIT License
Classifier: Programming Language :: Python :: 3.9
License-File: LICENSE
Requires-Dist: numpy <2
Requires-Dist: scipy
Requires-Dist: pandas
Requires-Dist: matplotlib
Requires-Dist: Bio
